igvf_subsample_db/__init__.py
igvf_subsample_db/create_rule_template.py
igvf_subsample_db/db.py
igvf_subsample_db/get_subsampled_uuids.py
igvf_subsample_db/profiles.py
igvf_subsample_db/subsample_pg.py
igvf_subsample_db-0.1.1.data/scripts/create_rule_template
igvf_subsample_db-0.1.1.data/scripts/get_subsampled_uuids
igvf_subsample_db-0.1.1.data/scripts/subsample_pg
igvf_subsample_db-0.1.1.dist-info/LICENSE
igvf_subsample_db-0.1.1.dist-info/METADATA
igvf_subsample_db-0.1.1.dist-info/WHEEL
igvf_subsample_db-0.1.1.dist-info/top_level.txt
igvf_subsample_db-0.1.1.dist-info/RECORD
